setup.cfg
setup.py
geontology/__init__.py
geontology.egg-info/PKG-INFO
geontology.egg-info/SOURCES.txt
geontology.egg-info/dependency_links.txt
geontology.egg-info/requires.txt
geontology.egg-info/top_level.txt