Metadata-Version: 1.0
Name: geontology
Version: 0.3.2
Summary: Support library for easier access to the GeoData ontology
Home-page: http://github.com/caspervg/geontology
Author: Casper Van Gheluwe
Author-email: casper.vangheluwe@ugent.be
License: MIT
Keywords: geodata geo ontology rdf rdflib
Platform: UNKNOWN
